Metadata-Version: 2.1
Name: flink-ml-tensorflow-nightly
Version: 0.4.dev20220123
Summary: UNKNOWN
Home-page: https://github.com/flink-extended/dl-on-flink
License: https://www.apache.org/licenses/LICENSE-2.0
Platform: UNKNOWN
Requires-Python: >=3.6,<3.8
Requires-Dist: tensorflow (<2.0.0,>=1.15.0)
Requires-Dist: tensorboard (<2.0.0,>=1.15.0)
Requires-Dist: flink-ml-framework-nightly (==0.4.dev20220123)
Requires-Dist: apache-flink (<1.15.0,>=1.14.0)
Requires-Dist: apache-flink-ml (==2.0.0)
